lidartopcd/__init__.py
lidartopcd/saver.py
lidartopcd-0.1.2.dist-info/licenses/LICENCE
lidartopcd-0.1.2.dist-info/METADATA
lidartopcd-0.1.2.dist-info/WHEEL
lidartopcd-0.1.2.dist-info/entry_points.txt
lidartopcd-0.1.2.dist-info/top_level.txt
lidartopcd-0.1.2.dist-info/RECORD
