Metadata-Version: 2.4
Name: lidartopcd
Version: 0.1.2
Summary: A ROS2 tool to save PCD files from LiDAR subscriptions with configurable processing
Author-email: Yakun <21bcs5128@cuchd.in>
Classifier: Programming Language :: Python :: 3
Classifier: License :: OSI Approved :: MIT License
Classifier: Operating System :: OS Independent
Requires-Python: >=3.10
License-File: LICENCE
Requires-Dist: numpy
Requires-Dist: scipy
Dynamic: license-file
